vplotly/__init__.py
vplotly/_est_test_properties.py
vplotly-0.0.4.dist-info/LICENSE
vplotly-0.0.4.dist-info/METADATA
vplotly-0.0.4.dist-info/WHEEL
vplotly-0.0.4.dist-info/RECORD
