Metadata-Version: 2.1
Name: vplotly
Version: 0.0.4
Summary: A small package for plotting based on plotly. This package is accompanying the package vstats.
License: MIT
Author: J. Janka
Requires-Python: >=3.8.1,<4.0
Classifier: License :: OSI Approved :: MIT License
Classifier: Programming Language :: Python :: 3
Classifier: Programming Language :: Python :: 3.9
Classifier: Programming Language :: Python :: 3.10
Classifier: Programming Language :: Python :: 3.11
Requires-Dist: kaleido (>=0.2.1)
Requires-Dist: numpy (>=1.19.5)
Requires-Dist: pandas (>=1.0.1)
Requires-Dist: plotly (>=5.15.0)
Requires-Dist: scipy (>=1.5.1)
Requires-Dist: statsmodels (>=0.12.0)
Requires-Dist: vstats (>=0.0.3)
